justai/__init__.py
justai/model/__init__.py
justai/model/message.py
justai/model/model.py
justai/models/anthropic_models.py
justai/models/basemodel.py
justai/models/deepseek_models.py
justai/models/gguf_models.py
justai/models/google_models.py
justai/models/modelfactory.py
justai/models/openai_completions.py
justai/models/openai_responses.py
justai/models/openrouter_models.py
justai/models/perplexity_models.py
justai/models/reve_models.py
justai/models/xai_models.py
justai/tools/__init__.py
justai/tools/cache.py
justai/tools/display.py
justai/tools/images.py
justai/tools/prompts.py
justai-5.4.0.dist-info/licenses/LICENSE
justai-5.4.0.dist-info/METADATA
justai-5.4.0.dist-info/WHEEL
justai-5.4.0.dist-info/top_level.txt
justai-5.4.0.dist-info/RECORD
