Metadata-Version: 2.4
Name: justai
Version: 5.4.0
Summary: Makes working with LLMs like OpenAI GPT, Anthropic Claude, Google Gemini and Open source models super easy
Author-email: HP Harmsen <hp@harmsen.nl>
License-Expression: MIT
Project-URL: Homepage, https://github.com/hpharmsen/justai
Keywords: OpenAI,ChatGPT,GPT-5,GPT5,api,Claude,Anthropic,Lllama,Gemini,Grok,Perplexity,Sonar
Classifier: Programming Language :: Python
Classifier: Programming Language :: Python :: 3
Requires-Python: >=3.10
License-File: LICENSE
Requires-Dist: absl-py
Requires-Dist: anthropic
Requires-Dist: google-genai
Requires-Dist: httpx
Requires-Dist: instructor
Requires-Dist: jsonschema
Requires-Dist: justdays
Requires-Dist: lxml
Requires-Dist: openai
Requires-Dist: pillow
Requires-Dist: pydantic
Requires-Dist: python-dateutil
Requires-Dist: python-dotenv
Requires-Dist: rich
Requires-Dist: tiktoken
Requires-Dist: tomli; python_version < "3.11"
Provides-Extra: dev
Requires-Dist: black; extra == "dev"
Requires-Dist: pytest; extra == "dev"
Requires-Dist: build; extra == "dev"
Requires-Dist: twine; extra == "dev"
Requires-Dist: nox; extra == "dev"
Provides-Extra: llama
Requires-Dist: llama-cpp-python; extra == "llama"
Dynamic: license-file
